simple_logger/__init__.py
simple_logger/logger.py
simple_logger/tests/__init__.py
simple_logger/tests/test_logger.py
python_simple_logger-1.0.6.dist-info/LICENSE
python_simple_logger-1.0.6.dist-info/METADATA
python_simple_logger-1.0.6.dist-info/WHEEL
python_simple_logger-1.0.6.dist-info/RECORD
